rng_rava_diag/__init__.py
rng_rava_diag/__main__.py
rng_rava_diag/rava_subapp_detailed_tests.py
rng_rava_diag/rava_subapp_quick_tests.py
rng_rava_diag/tests_bytes.py
rng_rava_diag/tests_nist.py
rng_rava_diag/tests_nums.py
rng_rava_diag/tests_pcs.py
rng_rava_diag/tests_pwm.py
rng_rava_diag/tests_report.py
rng_rava_diag/tests_tools.py
rng_rava_diag-1.2.0.dist-info/LICENSE
rng_rava_diag-1.2.0.dist-info/METADATA
rng_rava_diag-1.2.0.dist-info/WHEEL
rng_rava_diag-1.2.0.dist-info/top_level.txt
rng_rava_diag-1.2.0.dist-info/RECORD
