Metadata-Version: 2.1
Name: rng_rava_diag
Version: 1.2.0
Summary: RAVA Python Diagnostics
Author-email: Gabriel Guerrer <gabrielguerrer@gmail.com>
Project-URL: Homepage, https://github.com/gabrielguerrer/rng_rava_diag_py
Classifier: Programming Language :: Python :: 3
Classifier: License :: OSI Approved :: MIT License
Classifier: Operating System :: OS Independent
Requires-Python: >=3.7
License-File: LICENSE
Requires-Dist: rng_rava>=2.0.0
Requires-Dist: numpy
Requires-Dist: matplotlib
Requires-Dist: scipy
Requires-Dist: lmfit
